layoutc/__init__.py
layoutc/__main__.py
layoutc/codec.py
layoutc/entity/__init__.py
layoutc/entity/json.py
layoutc/entity/png.py
layoutc-0.2.2.dist-info/licenses/LICENSE
layoutc-0.2.2.dist-info/METADATA
layoutc-0.2.2.dist-info/WHEEL
layoutc-0.2.2.dist-info/entry_points.txt
layoutc-0.2.2.dist-info/top_level.txt
layoutc-0.2.2.dist-info/RECORD
