Metadata-Version: 2.4
Name: layoutc
Version: 0.2.2
Summary: Speedball arenas to splatmap atlases.
Author-email: Infima Labs <infimalabs@infimalabs.com>
License-Expression: MIT
Project-URL: Homepage, https://github.com/infimalabs/layoutc
Project-URL: Repository, https://github.com/infimalabs/layoutc.git
Project-URL: Issues, https://github.com/infimalabs/layoutc/issues
Classifier: Development Status :: 4 - Beta
Classifier: Intended Audience :: Developers
Classifier: Programming Language :: Python :: 3
Classifier: Programming Language :: Python :: 3.10
Classifier: Programming Language :: Python :: 3.11
Classifier: Programming Language :: Python :: 3.12
Classifier: Operating System :: OS Independent
Classifier: Topic :: Games/Entertainment
Classifier: Topic :: Multimedia :: Graphics :: Graphics Conversion
Classifier: Topic :: Scientific/Engineering :: Visualization
Requires-Python: >=3.10
License-File: LICENSE
Requires-Dist: defusedxml
Requires-Dist: numpy
Requires-Dist: pytest
Requires-Dist: Pillow
Provides-Extra: dev
Requires-Dist: ipython; extra == "dev"
Dynamic: license-file
